<?xml version="1.0" encoding="utf-8"?>
<Return returnVersion="2021v4.2" xmlns="http://www.irs.gov/efile">
  <ReturnHeader binaryAttachmentCnt="0">
    <ReturnTs>2023-12-14T14:43:49Z</ReturnTs>
    <TaxPeriodEndDt>2021-12-31</TaxPeriodEndDt>
    <PreparerFirmGrp>
      <PreparerFirmEIN>571011062</PreparerFirmEIN>
      <PreparerFirmName>
        <BusinessNameLine1Txt>H AND R BLOCK</BusinessNameLine1Txt>
      </PreparerFirmName>
      <PreparerUSAddress>
        <AddressLine1Txt>1724 HWY 501</AddressLine1Txt>
        <CityNm>MYRTLE BEACH</CityNm>
        <StateAbbreviationCd>SC</StateAbbreviationCd>
        <ZIPCd>29577</ZIPCd>
      </PreparerUSAddress>
    </PreparerFirmGrp>
    <ReturnTypeCd>990</ReturnTypeCd>
    <TaxPeriodBeginDt>2021-01-01</TaxPeriodBeginDt>
    <Filer>
      <EIN>832836137</EIN>
      <BusinessName>
        <BusinessNameLine1Txt>HOPEFUL RESTORATION GROUP INC</BusinessNameLine1Txt>
      </BusinessName>
      <BusinessNameControlTxt>HOPE</BusinessNameControlTxt>
      <PhoneNum>8436509096</PhoneNum>
      <USAddress>
        <AddressLine1Txt>2337 FRANK GORE ROAD</AddressLine1Txt>
        <CityNm>Little River</CityNm>
        <StateAbbreviationCd>SC</StateAbbreviationCd>
        <ZIPCd>29566</ZIPCd>
      </USAddress>
    </Filer>
    <BusinessOfficerGrp>
      <PersonNm>SHANE ZOCCOLE</PersonNm>
      <PersonTitleTxt>OWNER</PersonTitleTxt>
      <PhoneNum>8436509096</PhoneNum>
      <SignatureDt>2023-12-14</SignatureDt>
      <DiscussWithPaidPreparerInd>false</DiscussWithPaidPreparerInd>
    </BusinessOfficerGrp>
    <SigningOfficerGrp>
      <PersonFullName>
        <PersonFirstNm>SHANE</PersonFirstNm>
        <PersonLastNm>ZOCCOLE</PersonLastNm>
      </PersonFullName>
    </SigningOfficerGrp>
    <PreparerPersonGrp>
      <PreparerPersonNm>Erma York</PreparerPersonNm>
      <PTIN>P00545115</PTIN>
      <PhoneNum>8004725625</PhoneNum>
      <PreparationDt>2023-12-14</PreparationDt>
    </PreparerPersonGrp>
    <TaxYr>2021</TaxYr>
    <BuildTS>2023-04-26 12:10:37Z</BuildTS>
  </ReturnHeader>
  <ReturnData documentCnt="3">
    <IRS990 documentId="4" referenceDocumentId="3">
      <PrincipalOfficerNm>SHANE ZOCCOLE</PrincipalOfficerNm>
      <USAddress>
        <AddressLine1Txt>2337 FRANK GORE RD</AddressLine1Txt>
        <CityNm>Little River</CityNm>
        <StateAbbreviationCd>SC</StateAbbreviationCd>
        <ZIPCd>29566</ZIPCd>
      </USAddress>
      <GrossReceiptsAmt>80613</GrossReceiptsAmt>
      <GroupReturnForAffiliatesInd>false</GroupReturnForAffiliatesInd>
      <Organization501c3Ind>X</Organization501c3Ind>
      <WebsiteAddressTxt>N/A</WebsiteAddressTxt>
      <TypeOfOrganizationCorpInd>X</TypeOfOrganizationCorpInd>
      <FormationYr>2018</FormationYr>
      <LegalDomicileStateCd>SC</LegalDomicileStateCd>
      <ActivityOrMissionDesc>SERVE THE COMMINITY IN TIMES OF DISASTER AND ACUTE CRISIS BY SERVING BASIC FOOD PROVISIONS AND ESSENTIAL HOME ITEMS AND HELPING REBUILD</ActivityOrMissionDesc>
      <VotingMembersGoverningBodyCnt>3</VotingMembersGoverningBodyCnt>
      <VotingMembersIndependentCnt>0</VotingMembersIndependentCnt>
      <TotalEmployeeCnt>0</TotalEmployeeCnt>
      <TotalVolunteersCnt>30</TotalVolunteersCnt>
      <TotalGrossUBIAmt>0</TotalGrossUBIAmt>
      <PYContributionsGrantsAmt>206244</PYContributionsGrantsAmt>
      <CYContributionsGrantsAmt>80613</CYContributionsGrantsAmt>
      <CYProgramServiceRevenueAmt>0</CYProgramServiceRevenueAmt>
      <CYInvestmentIncomeAmt>0</CYInvestmentIncomeAmt>
      <CYOtherRevenueAmt>0</CYOtherRevenueAmt>
      <PYTotalRevenueAmt>206244</PYTotalRevenueAmt>
      <CYTotalRevenueAmt>80613</CYTotalRevenueAmt>
      <CYGrantsAndSimilarPaidAmt>0</CYGrantsAndSimilarPaidAmt>
      <CYBenefitsPaidToMembersAmt>0</CYBenefitsPaidToMembersAmt>
      <CYSalariesCompEmpBnftPaidAmt>0</CYSalariesCompEmpBnftPaidAmt>
      <CYTotalProfFndrsngExpnsAmt>0</CYTotalProfFndrsngExpnsAmt>
      <CYTotalFundraisingExpenseAmt>0</CYTotalFundraisingExpenseAmt>
      <PYOtherExpensesAmt>53168</PYOtherExpensesAmt>
      <CYOtherExpensesAmt>43626</CYOtherExpensesAmt>
      <PYTotalExpensesAmt>53168</PYTotalExpensesAmt>
      <CYTotalExpensesAmt>43626</CYTotalExpensesAmt>
      <PYRevenuesLessExpensesAmt>153076</PYRevenuesLessExpensesAmt>
      <CYRevenuesLessExpensesAmt>36987</CYRevenuesLessExpensesAmt>
      <TotalAssetsBOYAmt>162730</TotalAssetsBOYAmt>
      <TotalAssetsEOYAmt>199717</TotalAssetsEOYAmt>
      <TotalLiabilitiesEOYAmt>0</TotalLiabilitiesEOYAmt>
      <NetAssetsOrFundBalancesBOYAmt>162730</NetAssetsOrFundBalancesBOYAmt>
      <NetAssetsOrFundBalancesEOYAmt>199717</NetAssetsOrFundBalancesEOYAmt>
      <MissionDesc>TO SERVE THE COMMUNITY AT EVERY LEVEL OFFERING SUPPORT TO THE MOST VULNERABLE PEOPLE AFTER A DISASTER OR ACUTE CRISIS</MissionDesc>
      <SignificantNewProgramSrvcInd>false</SignificantNewProgramSrvcInd>
      <SignificantChangeInd>false</SignificantChangeInd>
      <ExpenseAmt>3444</ExpenseAmt>
      <Desc>SERVED THE COMMUNITY AT EVERY LEVEL OFFERING SUPPORT TO THE MOST VULNERABLE PEOPLE AFTER A DISASTER</Desc>
      <TotalProgramServiceExpensesAmt>3444</TotalProgramServiceExpensesAmt>
      <DescribedInSection501c3Ind referenceDocumentId="2">true</DescribedInSection501c3Ind>
      <ScheduleBRequiredInd>false</ScheduleBRequiredInd>
      <PoliticalCampaignActyInd>false</PoliticalCampaignActyInd>
      <LobbyingActivitiesInd>false</LobbyingActivitiesInd>
      <DonorAdvisedFundInd>false</DonorAdvisedFundInd>
      <ConservationEasementsInd>false</ConservationEasementsInd>
      <CollectionsOfArtInd>false</CollectionsOfArtInd>
      <CreditCounselingInd>false</CreditCounselingInd>
      <DonorRstrOrQuasiEndowmentsInd>false</DonorRstrOrQuasiEndowmentsInd>
      <ReportLandBuildingEquipmentInd>false</ReportLandBuildingEquipmentInd>
      <ReportInvestmentsOtherSecInd>false</ReportInvestmentsOtherSecInd>
      <ReportProgramRelatedInvstInd>false</ReportProgramRelatedInvstInd>
      <ReportOtherAssetsInd>false</ReportOtherAssetsInd>
      <ReportOtherLiabilitiesInd>false</ReportOtherLiabilitiesInd>
      <IncludeFIN48FootnoteInd>false</IncludeFIN48FootnoteInd>
      <IndependentAuditFinclStmtInd>false</IndependentAuditFinclStmtInd>
      <ConsolidatedAuditFinclStmtInd>false</ConsolidatedAuditFinclStmtInd>
      <SchoolOperatingInd>false</SchoolOperatingInd>
      <ForeignOfficeInd>false</ForeignOfficeInd>
      <ForeignActivitiesInd>false</ForeignActivitiesInd>
      <MoreThan5000KToOrgInd>false</MoreThan5000KToOrgInd>
      <MoreThan5000KToIndividualsInd>false</MoreThan5000KToIndividualsInd>
      <ProfessionalFundraisingInd>false</ProfessionalFundraisingInd>
      <FundraisingActivitiesInd>false</FundraisingActivitiesInd>
      <GamingActivitiesInd>false</GamingActivitiesInd>
      <OperateHospitalInd>false</OperateHospitalInd>
      <GrantsToOrganizationsInd>false</GrantsToOrganizationsInd>
      <GrantsToIndividualsInd>false</GrantsToIndividualsInd>
      <ScheduleJRequiredInd>false</ScheduleJRequiredInd>
      <TaxExemptBondsInd>false</TaxExemptBondsInd>
      <EngagedInExcessBenefitTransInd>false</EngagedInExcessBenefitTransInd>
      <PYExcessBenefitTransInd>false</PYExcessBenefitTransInd>
      <LoanOutstandingInd>false</LoanOutstandingInd>
      <GrantToRelatedPersonInd>false</GrantToRelatedPersonInd>
      <BusinessRlnWithOrgMemInd>false</BusinessRlnWithOrgMemInd>
      <BusinessRlnWithFamMemInd>false</BusinessRlnWithFamMemInd>
      <BusinessRlnWith35CtrlEntInd>false</BusinessRlnWith35CtrlEntInd>
      <DeductibleNonCashContriInd>false</DeductibleNonCashContriInd>
      <DeductibleArtContributionInd>false</DeductibleArtContributionInd>
      <TerminateOperationsInd>false</TerminateOperationsInd>
      <PartialLiquidationInd>false</PartialLiquidationInd>
      <DisregardedEntityInd>false</DisregardedEntityInd>
      <RelatedEntityInd>false</RelatedEntityInd>
      <RelatedOrganizationCtrlEntInd>false</RelatedOrganizationCtrlEntInd>
      <TrnsfrExmptNonChrtblRltdOrgInd>false</TrnsfrExmptNonChrtblRltdOrgInd>
      <ActivitiesConductedPrtshpInd>false</ActivitiesConductedPrtshpInd>
      <ScheduleORequiredInd>false</ScheduleORequiredInd>
      <IRPDocumentCnt>0</IRPDocumentCnt>
      <IRPDocumentW2GCnt>0</IRPDocumentW2GCnt>
      <BackupWthldComplianceInd>false</BackupWthldComplianceInd>
      <EmployeeCnt>0</EmployeeCnt>
      <UnrelatedBusIncmOverLimitInd>false</UnrelatedBusIncmOverLimitInd>
      <ForeignFinancialAccountInd>false</ForeignFinancialAccountInd>
      <ProhibitedTaxShelterTransInd>false</ProhibitedTaxShelterTransInd>
      <TaxablePartyNotificationInd>false</TaxablePartyNotificationInd>
      <NondeductibleContributionsInd>false</NondeductibleContributionsInd>
      <QuidProQuoContributionsInd>false</QuidProQuoContributionsInd>
      <Form8282PropertyDisposedOfInd>false</Form8282PropertyDisposedOfInd>
      <RcvFndsToPayPrsnlBnftCntrctInd>false</RcvFndsToPayPrsnlBnftCntrctInd>
      <PayPremiumsPrsnlBnftCntrctInd>false</PayPremiumsPrsnlBnftCntrctInd>
      <Form8899Filedind>false</Form8899Filedind>
      <Form1098CFiledInd>false</Form1098CFiledInd>
      <DAFExcessBusinessHoldingsInd>false</DAFExcessBusinessHoldingsInd>
      <TaxableDistributionsInd>false</TaxableDistributionsInd>
      <DistributionToDonorInd>false</DistributionToDonorInd>
      <OrgFiledInLieuOfForm1041Ind>false</OrgFiledInLieuOfForm1041Ind>
      <TaxExemptInterestAmt>0</TaxExemptInterestAmt>
      <LicensedMoreThanOneStateInd>false</LicensedMoreThanOneStateInd>
      <IndoorTanningServicesInd>false</IndoorTanningServicesInd>
      <SubjToTaxRmnrtnExPrchtPymtInd>false</SubjToTaxRmnrtnExPrchtPymtInd>
      <SubjectToExcsTaxNetInvstIncInd>false</SubjectToExcsTaxNetInvstIncInd>
      <GoverningBodyVotingMembersCnt>3</GoverningBodyVotingMembersCnt>
      <IndependentVotingMemberCnt>0</IndependentVotingMemberCnt>
      <FamilyOrBusinessRlnInd>false</FamilyOrBusinessRlnInd>
      <DelegationOfMgmtDutiesInd>false</DelegationOfMgmtDutiesInd>
      <ChangeToOrgDocumentsInd>false</ChangeToOrgDocumentsInd>
      <MaterialDiversionOrMisuseInd>false</MaterialDiversionOrMisuseInd>
      <MembersOrStockholdersInd>false</MembersOrStockholdersInd>
      <ElectionOfBoardMembersInd>false</ElectionOfBoardMembersInd>
      <DecisionsSubjectToApprovaInd>false</DecisionsSubjectToApprovaInd>
      <MinutesOfGoverningBodyInd>false</MinutesOfGoverningBodyInd>
      <MinutesOfCommitteesInd>false</MinutesOfCommitteesInd>
      <OfficerMailingAddressInd>false</OfficerMailingAddressInd>
      <LocalChaptersInd>false</LocalChaptersInd>
      <Form990ProvidedToGvrnBodyInd>false</Form990ProvidedToGvrnBodyInd>
      <ConflictOfInterestPolicyInd>false</ConflictOfInterestPolicyInd>
      <RegularMonitoringEnfrcInd>false</RegularMonitoringEnfrcInd>
      <WhistleblowerPolicyInd>false</WhistleblowerPolicyInd>
      <DocumentRetentionPolicyInd>false</DocumentRetentionPolicyInd>
      <CompensationProcessCEOInd>false</CompensationProcessCEOInd>
      <CompensationProcessOtherInd>false</CompensationProcessOtherInd>
      <InvestmentInJointVentureInd>false</InvestmentInJointVentureInd>
      <StatesWhereCopyOfReturnIsFldCd>SC</StatesWhereCopyOfReturnIsFldCd>
      <BooksInCareOfDetail>
        <PersonNm>SHANE ZOCCOLE</PersonNm>
        <PhoneNum>8436509096</PhoneNum>
        <USAddress>
          <AddressLine1Txt>2337 FRANK GORE RD</AddressLine1Txt>
          <CityNm>FPO</CityNm>
          <StateAbbreviationCd>AE</StateAbbreviationCd>
          <ZIPCd>09566</ZIPCd>
        </USAddress>
      </BooksInCareOfDetail>
      <NoListedPersonsCompensatedInd>X</NoListedPersonsCompensatedInd>
      <Form990PartVIISectionAGrp>
        <PersonNm>SHANE ZOCCOLE</PersonNm>
        <TitleTxt>OWNER</TitleTxt>
        <AverageHoursPerWeekRt>60.00</AverageHoursPerWeekRt>
        <OfficerInd>X</OfficerInd>
        <ReportableCompFromOrgAmt>0</ReportableCompFromOrgAmt>
        <ReportableCompFromRltdOrgAmt>0</ReportableCompFromRltdOrgAmt>
        <OtherCompensationAmt>0</OtherCompensationAmt>
      </Form990PartVIISectionAGrp>
      <FormerOfcrEmployeesListedInd>false</FormerOfcrEmployeesListedInd>
      <TotalCompGreaterThan150KInd>false</TotalCompGreaterThan150KInd>
      <CompensationFromOtherSrcsInd>false</CompensationFromOtherSrcsInd>
      <AllOtherContributionsAmt>80613</AllOtherContributionsAmt>
      <TotalContributionsAmt>80613</TotalContributionsAmt>
      <TotalRevenueGrp>
        <TotalRevenueColumnAmt>80613</TotalRevenueColumnAmt>
      </TotalRevenueGrp>
      <OfficeExpensesGrp>
        <TotalAmt>3444</TotalAmt>
        <ManagementAndGeneralAmt>3444</ManagementAndGeneralAmt>
      </OfficeExpensesGrp>
      <OccupancyGrp>
        <TotalAmt>8957</TotalAmt>
        <ProgramServicesAmt>8957</ProgramServicesAmt>
      </OccupancyGrp>
      <TravelGrp>
        <TotalAmt>3211</TotalAmt>
        <ProgramServicesAmt>3211</ProgramServicesAmt>
      </TravelGrp>
      <DepreciationDepletionGrp>
        <TotalAmt>2952</TotalAmt>
      </DepreciationDepletionGrp>
      <InsuranceGrp>
        <TotalAmt>440</TotalAmt>
        <ProgramServicesAmt>440</ProgramServicesAmt>
      </InsuranceGrp>
      <OtherExpensesGrp>
        <Desc>PRINTING</Desc>
        <TotalAmt>649</TotalAmt>
        <ProgramServicesAmt>649</ProgramServicesAmt>
      </OtherExpensesGrp>
      <OtherExpensesGrp>
        <Desc>INTERNET SERVICES</Desc>
        <TotalAmt>891</TotalAmt>
        <ProgramServicesAmt>891</ProgramServicesAmt>
      </OtherExpensesGrp>
      <OtherExpensesGrp>
        <Desc>SUPPLIES</Desc>
        <TotalAmt>17985</TotalAmt>
        <ProgramServicesAmt>17985</ProgramServicesAmt>
      </OtherExpensesGrp>
      <OtherExpensesGrp>
        <Desc>EQUIPMENT RENTAL</Desc>
        <TotalAmt>4129</TotalAmt>
        <ProgramServicesAmt>4129</ProgramServicesAmt>
      </OtherExpensesGrp>
      <AllOtherExpensesGrp>
        <TotalAmt>968</TotalAmt>
        <ProgramServicesAmt>968</ProgramServicesAmt>
      </AllOtherExpensesGrp>
      <TotalFunctionalExpensesGrp>
        <TotalAmt>43626</TotalAmt>
        <ProgramServicesAmt>37230</ProgramServicesAmt>
        <ManagementAndGeneralAmt>3444</ManagementAndGeneralAmt>
        <FundraisingAmt>0</FundraisingAmt>
      </TotalFunctionalExpensesGrp>
      <CashNonInterestBearingGrp>
        <BOYAmt>126008</BOYAmt>
        <EOYAmt>105443</EOYAmt>
      </CashNonInterestBearingGrp>
      <LandBldgEquipCostOrOtherBssAmt>12053</LandBldgEquipCostOrOtherBssAmt>
      <LandBldgEquipAccumDeprecAmt>4674</LandBldgEquipAccumDeprecAmt>
      <LandBldgEquipBasisNetGrp>
        <BOYAmt>10331</BOYAmt>
        <EOYAmt>7379</EOYAmt>
      </LandBldgEquipBasisNetGrp>
      <IntangibleAssetsGrp>
        <BOYAmt>26391</BOYAmt>
        <EOYAmt>86895</EOYAmt>
      </IntangibleAssetsGrp>
      <TotalAssetsGrp>
        <BOYAmt>162730</BOYAmt>
        <EOYAmt>199717</EOYAmt>
      </TotalAssetsGrp>
      <TotalLiabilitiesGrp>
        <BOYAmt>0</BOYAmt>
        <EOYAmt>0</EOYAmt>
      </TotalLiabilitiesGrp>
      <TotalNetAssetsFundBalanceGrp>
        <BOYAmt>162730</BOYAmt>
        <EOYAmt>199717</EOYAmt>
      </TotalNetAssetsFundBalanceGrp>
      <TotLiabNetAssetsFundBalanceGrp>
        <BOYAmt>162730</BOYAmt>
        <EOYAmt>199717</EOYAmt>
      </TotLiabNetAssetsFundBalanceGrp>
      <ReconcilationRevenueExpnssAmt>36987</ReconcilationRevenueExpnssAmt>
      <MethodOfAccountingCashInd>X</MethodOfAccountingCashInd>
      <AccountantCompileOrReviewInd>false</AccountantCompileOrReviewInd>
      <FSAuditedInd>false</FSAuditedInd>
      <FederalGrantAuditRequiredInd>false</FederalGrantAuditRequiredInd>
    </IRS990>
    <IRS990ScheduleA documentId="2">
      <PubliclySupportedOrg509a2Ind>X</PubliclySupportedOrg509a2Ind>
      <GiftsGrantsContrisRcvd509Grp>
        <CurrentTaxYearMinus2YearsAmt>40698</CurrentTaxYearMinus2YearsAmt>
        <CurrentTaxYearMinus1YearAmt>80613</CurrentTaxYearMinus1YearAmt>
        <CurrentTaxYearAmt>206244</CurrentTaxYearAmt>
        <TotalAmt>327555</TotalAmt>
      </GiftsGrantsContrisRcvd509Grp>
      <Total509Grp>
        <CurrentTaxYearMinus2YearsAmt>40698</CurrentTaxYearMinus2YearsAmt>
        <CurrentTaxYearMinus1YearAmt>80613</CurrentTaxYearMinus1YearAmt>
        <CurrentTaxYearAmt>206244</CurrentTaxYearAmt>
        <TotalAmt>327555</TotalAmt>
      </Total509Grp>
      <PublicSupportTotal509Amt>327555</PublicSupportTotal509Amt>
      <TotalSupportCalendarYearGrp>
        <CurrentTaxYearMinus2YearsAmt>40698</CurrentTaxYearMinus2YearsAmt>
        <CurrentTaxYearMinus1YearAmt>80613</CurrentTaxYearMinus1YearAmt>
        <CurrentTaxYearAmt>206244</CurrentTaxYearAmt>
        <TotalAmt>327555</TotalAmt>
      </TotalSupportCalendarYearGrp>
      <PublicSupportCY509Pct>1.00000</PublicSupportCY509Pct>
      <InvestmentIncomeCYPct>0.00000</InvestmentIncomeCYPct>
      <ThirtyThrPctSuprtTestsCY509Ind>X</ThirtyThrPctSuprtTestsCY509Ind>
    </IRS990ScheduleA>
    <IRS990ScheduleO documentId="3">
      <SupplementalInformationDetail>
        <FormAndLineReferenceDesc>PART VI SECTION A</FormAndLineReferenceDesc>
        <ExplanationTxt>THEIR ARE THREE VOTING MEMBERS. ALL MEMBERS ARE NOT PAID A SALARY</ExplanationTxt>
      </SupplementalInformationDetail>
      <SupplementalInformationDetail>
        <FormAndLineReferenceDesc>PART III LINE 4A</FormAndLineReferenceDesc>
        <ExplanationTxt>HOPEFUL RESTORATION HAS ELPED MANY PEOPLE DURING DISASTERS IN THE PAST YEAR</ExplanationTxt>
      </SupplementalInformationDetail>
    </IRS990ScheduleO>
  </ReturnData>
</Return>