<?xml version="1.0" encoding="utf-8"?>
<Return xmlns="http://www.irs.gov/efile" xmlns:xsi="http://www.w3.org/2001/XMLSchema-instance" xsi:schemaLocation="http://www.irs.gov/efile" returnVersion="2022v5.0">
  <ReturnHeader binaryAttachmentCnt="0">
    <ReturnTs>2023-12-12T07:44:27-06:00</ReturnTs>
    <TaxPeriodEndDt>2023-07-31</TaxPeriodEndDt>
    <PreparerFirmGrp>
      <PreparerFirmEIN>390758449</PreparerFirmEIN>
      <PreparerFirmName>
        <BusinessNameLine1Txt>WIPFLI LLP</BusinessNameLine1Txt>
      </PreparerFirmName>
      <PreparerUSAddress>
        <AddressLine1Txt>1502 LONDON ROAD SUITE 200</AddressLine1Txt>
        <CityNm>DULUTH</CityNm>
        <StateAbbreviationCd>MN</StateAbbreviationCd>
        <ZIPCd>55812</ZIPCd>
      </PreparerUSAddress>
    </PreparerFirmGrp>
    <ReturnTypeCd>990EZ</ReturnTypeCd>
    <TaxPeriodBeginDt>2022-08-01</TaxPeriodBeginDt>
    <Filer>
      <EIN>462763645</EIN>
      <BusinessName>
        <BusinessNameLine1Txt>ST FRANCIS HIGH SCHOOL FATHER'S CLUB</BusinessNameLine1Txt>
      </BusinessName>
      <BusinessNameControlTxt>STFR</BusinessNameControlTxt>
      <PhoneNum>6306685800</PhoneNum>
      <USAddress>
        <AddressLine1Txt>2130 ROOSEVELT RD</AddressLine1Txt>
        <CityNm>WHEATON</CityNm>
        <StateAbbreviationCd>IL</StateAbbreviationCd>
        <ZIPCd>60187</ZIPCd>
      </USAddress>
    </Filer>
    <BusinessOfficerGrp>
      <PersonNm>BRIAN BLAHA</PersonNm>
      <PersonTitleTxt>TREASURER</PersonTitleTxt>
      <PhoneNum>9205623068</PhoneNum>
      <SignatureDt>2023-12-11</SignatureDt>
      <DiscussWithPaidPreparerInd>1</DiscussWithPaidPreparerInd>
    </BusinessOfficerGrp>
    <SigningOfficerGrp>
      <PersonFullName>
        <PersonFirstNm>BRIAN</PersonFirstNm>
        <PersonLastNm>BLAHA</PersonLastNm>
      </PersonFullName>
      <SSN>999009999</SSN>
    </SigningOfficerGrp>
    <IRSResponsiblePrtyInfoCurrInd>0</IRSResponsiblePrtyInfoCurrInd>
    <PreparerPersonGrp>
      <PreparerPersonNm>MICHAEL J PETERSON CPA</PreparerPersonNm>
      <PTIN>P01833529</PTIN>
      <PhoneNum>2187224705</PhoneNum>
      <PreparationDt>2023-12-11</PreparationDt>
    </PreparerPersonGrp>
    <AdditionalFilerInformation>
      <TrustedCustomerGrp>
        <TrustedCustomerCd>2</TrustedCustomerCd>
        <AuthenticationAssuranceLevelCd>AAL1</AuthenticationAssuranceLevelCd>
        <IdentityAssuranceLevelCd>IAL1</IdentityAssuranceLevelCd>
      </TrustedCustomerGrp>
    </AdditionalFilerInformation>
    <TaxYr>2022</TaxYr>
    <BuildTS>2023-04-26 12:10:37Z</BuildTS>
  </ReturnHeader>
  <ReturnData documentCnt="5">
    <IRS990EZ documentId="RetDoc1234200001" referenceDocumentId="RetDoc1051800001 RetDoc2278000001">
      <MethodOfAccountingCashInd>X</MethodOfAccountingCashInd>
      <ScheduleBNotRequiredInd>X</ScheduleBNotRequiredInd>
      <WebsiteAddressTxt>WWW.STFRANCISFATHERSCLUB.COM</WebsiteAddressTxt>
      <Organization501c3Ind referenceDocumentId="RetDoc1039100001">X</Organization501c3Ind>
      <TypeOfOrganizationCorpInd>X</TypeOfOrganizationCorpInd>
      <GrossReceiptsAmt>116266</GrossReceiptsAmt>
      <InfoInScheduleOPartIInd>X</InfoInScheduleOPartIInd>
      <ContributionsGiftsGrantsEtcAmt>32456</ContributionsGiftsGrantsEtcAmt>
      <FundraisingGrossIncomeAmt referenceDocumentId="RetDoc1041300001">83810</FundraisingGrossIncomeAmt>
      <SpecialEventsDirectExpensesAmt>41887</SpecialEventsDirectExpensesAmt>
      <SpecialEventsNetIncomeLossAmt>41923</SpecialEventsNetIncomeLossAmt>
      <TotalRevenueAmt>74379</TotalRevenueAmt>
      <GrantsAndSimilarAmountsPaidAmt>43600</GrantsAndSimilarAmountsPaidAmt>
      <OtherExpensesTotalAmt>17155</OtherExpensesTotalAmt>
      <TotalExpensesAmt>60755</TotalExpensesAmt>
      <ExcessOrDeficitForYearAmt>13624</ExcessOrDeficitForYearAmt>
      <NetAssetsOrFundBalancesBOYAmt>72782</NetAssetsOrFundBalancesBOYAmt>
      <OtherChangesInNetAssetsAmt>0</OtherChangesInNetAssetsAmt>
      <NetAssetsOrFundBalancesEOYAmt>86406</NetAssetsOrFundBalancesEOYAmt>
      <InfoInScheduleOPartIIInd>X</InfoInScheduleOPartIIInd>
      <CashSavingsAndInvestmentsGrp>
        <BOYAmt>72782</BOYAmt>
        <EOYAmt>85856</EOYAmt>
      </CashSavingsAndInvestmentsGrp>
      <OtherAssetsTotalDetail>
        <BOYAmt>0</BOYAmt>
        <EOYAmt>550</EOYAmt>
      </OtherAssetsTotalDetail>
      <Form990TotalAssetsGrp>
        <BOYAmt>72782</BOYAmt>
        <EOYAmt>86406</EOYAmt>
      </Form990TotalAssetsGrp>
      <SumOfTotalLiabilitiesGrp>
        <BOYAmt>0</BOYAmt>
        <EOYAmt>0</EOYAmt>
      </SumOfTotalLiabilitiesGrp>
      <NetAssetsOrFundBalancesGrp>
        <BOYAmt>72782</BOYAmt>
        <EOYAmt>86406</EOYAmt>
      </NetAssetsOrFundBalancesGrp>
      <InfoInScheduleOPartIIIInd>X</InfoInScheduleOPartIIIInd>
      <PrimaryExemptPurposeTxt>TO PROVIDE EDUCATIONAL EQUIPMENT AND FINANCIAL SUPPORT FOR THE IMPROVEMENT OF THE EDUCATIONAL FACILITIES OF ST. FRANCIS HIGH SCHOOL, WHEATON, IL., AND TO PROVIDE TUITION ASSISTANCE TO ANY SCHOOL STUDENT WHO MAY SUFFER THE LOSS OF A PARENT OR GUARDIAN DUE TO DEATH OF SERIOUS DISABILITY WHICH RESULTS IN THE STUDENT'S INABILITY TO PAY SOME OR ALL OF THE TUITION NEEDED TO COMPLETE THEIR HIGH SCHOOL EDUCATION AT ST. FRANCIS HIGH SCHOOL.</PrimaryExemptPurposeTxt>
      <ProgramSrvcAccomplishmentGrp>
        <DescriptionProgramSrvcAccomTxt>ACTIVITIES CONDUCTED ENABLE THE ORGANIZATION TO PROVIDE EDUCATIONAL MATERIALS AND FINANCIAL SUPPORT TO ST. FRANCIS HIGH SCHOOL, WHEATON, IL FOR THE BETTER EDUCATION OF ITS STUDENTS</DescriptionProgramSrvcAccomTxt>
        <GrantsAndAllocationsAmt>0</GrantsAndAllocationsAmt>
        <ProgramServiceExpensesAmt>0</ProgramServiceExpensesAmt>
      </ProgramSrvcAccomplishmentGrp>
      <TotalProgramServiceExpensesAmt>0</TotalProgramServiceExpensesAmt>
      <InfoInScheduleOPartIVInd>X</InfoInScheduleOPartIVInd>
      <OfficerDirectorTrusteeEmplGrp>
        <PersonNm>FRANK BUCARO</PersonNm>
        <TitleTxt>DIRECTOR</TitleTxt>
        <AverageHrsPerWkDevotedToPosRt>2.00</AverageHrsPerWkDevotedToPosRt>
        <CompensationAmt>0</CompensationAmt>
        <EmployeeBenefitProgramAmt>0</EmployeeBenefitProgramAmt>
        <ExpenseAccountOtherAllwncAmt>0</ExpenseAccountOtherAllwncAmt>
      </OfficerDirectorTrusteeEmplGrp>
      <OfficerDirectorTrusteeEmplGrp>
        <PersonNm>DAVID BAFFA</PersonNm>
        <TitleTxt>DIRECTOR</TitleTxt>
        <AverageHrsPerWkDevotedToPosRt>2.00</AverageHrsPerWkDevotedToPosRt>
        <CompensationAmt>0</CompensationAmt>
        <EmployeeBenefitProgramAmt>0</EmployeeBenefitProgramAmt>
        <ExpenseAccountOtherAllwncAmt>0</ExpenseAccountOtherAllwncAmt>
      </OfficerDirectorTrusteeEmplGrp>
      <OfficerDirectorTrusteeEmplGrp>
        <PersonNm>MARK FASSNACHT</PersonNm>
        <TitleTxt>DIRECTOR</TitleTxt>
        <AverageHrsPerWkDevotedToPosRt>4.00</AverageHrsPerWkDevotedToPosRt>
        <CompensationAmt>0</CompensationAmt>
        <EmployeeBenefitProgramAmt>0</EmployeeBenefitProgramAmt>
        <ExpenseAccountOtherAllwncAmt>0</ExpenseAccountOtherAllwncAmt>
      </OfficerDirectorTrusteeEmplGrp>
      <OfficerDirectorTrusteeEmplGrp>
        <PersonNm>JOE GNORSKI</PersonNm>
        <TitleTxt>DIRECTOR</TitleTxt>
        <AverageHrsPerWkDevotedToPosRt>4.00</AverageHrsPerWkDevotedToPosRt>
        <CompensationAmt>0</CompensationAmt>
        <EmployeeBenefitProgramAmt>0</EmployeeBenefitProgramAmt>
        <ExpenseAccountOtherAllwncAmt>0</ExpenseAccountOtherAllwncAmt>
      </OfficerDirectorTrusteeEmplGrp>
      <OfficerDirectorTrusteeEmplGrp>
        <PersonNm>JIM WOLF</PersonNm>
        <TitleTxt>DIRECTOR</TitleTxt>
        <AverageHrsPerWkDevotedToPosRt>2.00</AverageHrsPerWkDevotedToPosRt>
        <CompensationAmt>0</CompensationAmt>
        <EmployeeBenefitProgramAmt>0</EmployeeBenefitProgramAmt>
        <ExpenseAccountOtherAllwncAmt>0</ExpenseAccountOtherAllwncAmt>
      </OfficerDirectorTrusteeEmplGrp>
      <OfficerDirectorTrusteeEmplGrp>
        <PersonNm>JOHN KING</PersonNm>
        <TitleTxt>DIRECTOR</TitleTxt>
        <AverageHrsPerWkDevotedToPosRt>2.00</AverageHrsPerWkDevotedToPosRt>
        <CompensationAmt>0</CompensationAmt>
        <EmployeeBenefitProgramAmt>0</EmployeeBenefitProgramAmt>
        <ExpenseAccountOtherAllwncAmt>0</ExpenseAccountOtherAllwncAmt>
      </OfficerDirectorTrusteeEmplGrp>
      <OfficerDirectorTrusteeEmplGrp>
        <PersonNm>NEAL LILLY</PersonNm>
        <TitleTxt>DIRECTOR</TitleTxt>
        <AverageHrsPerWkDevotedToPosRt>2.00</AverageHrsPerWkDevotedToPosRt>
        <CompensationAmt>0</CompensationAmt>
        <EmployeeBenefitProgramAmt>0</EmployeeBenefitProgramAmt>
        <ExpenseAccountOtherAllwncAmt>0</ExpenseAccountOtherAllwncAmt>
      </OfficerDirectorTrusteeEmplGrp>
      <OfficerDirectorTrusteeEmplGrp>
        <PersonNm>BRIAN FLOOD</PersonNm>
        <TitleTxt>FOUNDER</TitleTxt>
        <AverageHrsPerWkDevotedToPosRt>1.00</AverageHrsPerWkDevotedToPosRt>
        <CompensationAmt>0</CompensationAmt>
        <EmployeeBenefitProgramAmt>0</EmployeeBenefitProgramAmt>
        <ExpenseAccountOtherAllwncAmt>0</ExpenseAccountOtherAllwncAmt>
      </OfficerDirectorTrusteeEmplGrp>
      <OfficerDirectorTrusteeEmplGrp>
        <PersonNm>NICK ADKINS</PersonNm>
        <TitleTxt>VICE PRESIDENT</TitleTxt>
        <AverageHrsPerWkDevotedToPosRt>4.00</AverageHrsPerWkDevotedToPosRt>
        <CompensationAmt>0</CompensationAmt>
        <EmployeeBenefitProgramAmt>0</EmployeeBenefitProgramAmt>
        <ExpenseAccountOtherAllwncAmt>0</ExpenseAccountOtherAllwncAmt>
      </OfficerDirectorTrusteeEmplGrp>
      <OfficerDirectorTrusteeEmplGrp>
        <PersonNm>TODD OLSON</PersonNm>
        <TitleTxt>PRESIDENT</TitleTxt>
        <AverageHrsPerWkDevotedToPosRt>4.00</AverageHrsPerWkDevotedToPosRt>
        <CompensationAmt>0</CompensationAmt>
        <EmployeeBenefitProgramAmt>0</EmployeeBenefitProgramAmt>
        <ExpenseAccountOtherAllwncAmt>0</ExpenseAccountOtherAllwncAmt>
      </OfficerDirectorTrusteeEmplGrp>
      <OfficerDirectorTrusteeEmplGrp>
        <PersonNm>JAMES KENNY</PersonNm>
        <TitleTxt>SECRETARY</TitleTxt>
        <AverageHrsPerWkDevotedToPosRt>4.00</AverageHrsPerWkDevotedToPosRt>
        <CompensationAmt>0</CompensationAmt>
        <EmployeeBenefitProgramAmt>0</EmployeeBenefitProgramAmt>
        <ExpenseAccountOtherAllwncAmt>0</ExpenseAccountOtherAllwncAmt>
      </OfficerDirectorTrusteeEmplGrp>
      <OfficerDirectorTrusteeEmplGrp>
        <PersonNm>BRIAN BLAHA</PersonNm>
        <TitleTxt>TREASURER</TitleTxt>
        <AverageHrsPerWkDevotedToPosRt>4.00</AverageHrsPerWkDevotedToPosRt>
        <CompensationAmt>0</CompensationAmt>
        <EmployeeBenefitProgramAmt>0</EmployeeBenefitProgramAmt>
        <ExpenseAccountOtherAllwncAmt>0</ExpenseAccountOtherAllwncAmt>
      </OfficerDirectorTrusteeEmplGrp>
      <InfoInScheduleOPartVInd>X</InfoInScheduleOPartVInd>
      <ActivitiesNotPreviouslyRptInd>0</ActivitiesNotPreviouslyRptInd>
      <ChgMadeToOrgnzngDocNotRptInd>0</ChgMadeToOrgnzngDocNotRptInd>
      <OrganizationHadUBIInd>0</OrganizationHadUBIInd>
      <SubjectToProxyTaxInd>0</SubjectToProxyTaxInd>
      <OrganizationDissolvedEtcInd>0</OrganizationDissolvedEtcInd>
      <DirectIndirectPltclExpendAmt>0</DirectIndirectPltclExpendAmt>
      <MadeLoansToFromOfficersInd>0</MadeLoansToFromOfficersInd>
      <TaxImposedUnderIRC4911Amt>0</TaxImposedUnderIRC4911Amt>
      <TaxImposedUnderIRC4912Amt>0</TaxImposedUnderIRC4912Amt>
      <TaxImposedUnderIRC4955Amt>0</TaxImposedUnderIRC4955Amt>
      <EngagedInExcessBenefitTransInd>0</EngagedInExcessBenefitTransInd>
      <TaxImposedOnOrganizationMgrAmt>0</TaxImposedOnOrganizationMgrAmt>
      <TaxReimbursedByOrganizationAmt>0</TaxReimbursedByOrganizationAmt>
      <ProhibitedTaxShelterTransInd>0</ProhibitedTaxShelterTransInd>
      <StatesWhereCopyOfReturnIsFldCd>IL</StatesWhereCopyOfReturnIsFldCd>
      <BooksInCareOfDetail>
        <PersonNm>BRIAN J BLAHA</PersonNm>
        <USAddress>
          <AddressLine1Txt>1706 E HAWTHORNE BLVD</AddressLine1Txt>
          <CityNm>WHEATON</CityNm>
          <StateAbbreviationCd>IL</StateAbbreviationCd>
          <ZIPCd>60187</ZIPCd>
        </USAddress>
        <PhoneNum>9205623068</PhoneNum>
      </BooksInCareOfDetail>
      <ForeignFinancialAccountInd>0</ForeignFinancialAccountInd>
      <ForeignOfficeInd>0</ForeignOfficeInd>
      <DonorAdvisedFndsInd>0</DonorAdvisedFndsInd>
      <OperateHospitalInd>0</OperateHospitalInd>
      <TanningServicesProvidedInd>0</TanningServicesProvidedInd>
      <RelatedOrganizationCtrlEntInd>0</RelatedOrganizationCtrlEntInd>
      <PoliticalCampaignActyInd>0</PoliticalCampaignActyInd>
      <LobbyingActivitiesInd>0</LobbyingActivitiesInd>
      <SchoolOperatingInd>0</SchoolOperatingInd>
      <TrnsfrExmptNonChrtblRltdOrgInd>0</TrnsfrExmptNonChrtblRltdOrgInd>
      <PartVIOfCompOfHghstPdEmplTxt>NONE</PartVIOfCompOfHghstPdEmplTxt>
      <PartVIHghstPdCntrctProfSrvcTxt>NONE</PartVIHghstPdCntrctProfSrvcTxt>
      <FiledScheduleAInd>1</FiledScheduleAInd>
    </IRS990EZ>
    <IRS990ScheduleA documentId="RetDoc1039100001">
      <PublicOrganization170Ind>X</PublicOrganization170Ind>
      <GiftsGrantsContriRcvd170Grp>
        <CurrentTaxYearMinus4YearsAmt>27630</CurrentTaxYearMinus4YearsAmt>
        <CurrentTaxYearMinus3YearsAmt>27620</CurrentTaxYearMinus3YearsAmt>
        <CurrentTaxYearMinus2YearsAmt>34518</CurrentTaxYearMinus2YearsAmt>
        <CurrentTaxYearMinus1YearAmt>33129</CurrentTaxYearMinus1YearAmt>
        <CurrentTaxYearAmt>32456</CurrentTaxYearAmt>
        <TotalAmt>155353</TotalAmt>
      </GiftsGrantsContriRcvd170Grp>
      <TotalCalendarYear170Grp>
        <CurrentTaxYearMinus4YearsAmt>27630</CurrentTaxYearMinus4YearsAmt>
        <CurrentTaxYearMinus3YearsAmt>27620</CurrentTaxYearMinus3YearsAmt>
        <CurrentTaxYearMinus2YearsAmt>34518</CurrentTaxYearMinus2YearsAmt>
        <CurrentTaxYearMinus1YearAmt>33129</CurrentTaxYearMinus1YearAmt>
        <CurrentTaxYearAmt>32456</CurrentTaxYearAmt>
        <TotalAmt>155353</TotalAmt>
      </TotalCalendarYear170Grp>
      <PublicSupportTotal170Amt>155353</PublicSupportTotal170Amt>
      <TotalSupportAmt>155353</TotalSupportAmt>
      <GrossReceiptsRltdActivitiesAmt>265449</GrossReceiptsRltdActivitiesAmt>
      <PublicSupportCY170Pct>1.00000</PublicSupportCY170Pct>
      <PublicSupportPY170Pct>1.00000</PublicSupportPY170Pct>
      <ThirtyThrPctSuprtTestsCY170Ind>X</ThirtyThrPctSuprtTestsCY170Ind>
    </IRS990ScheduleA>
    <IRS990ScheduleG documentId="RetDoc1041300001">
      <FundraisingEventInformationGrp>
        <Event1Nm>BOXING NIGHT</Event1Nm>
        <GrossReceiptsEvent1Amt>56326</GrossReceiptsEvent1Amt>
        <GrossRevenueEvent1Amt>56326</GrossRevenueEvent1Amt>
        <CashPrizesEvent1Amt>1010</CashPrizesEvent1Amt>
        <RentFacilityCostsEvent1Amt>1836</RentFacilityCostsEvent1Amt>
        <FoodAndBeverageEvent1Amt>8869</FoodAndBeverageEvent1Amt>
        <OtherDirectExpensesEvent1Amt>17628</OtherDirectExpensesEvent1Amt>
        <Event2Nm>RAFFLES, SPORT</Event2Nm>
        <GrossReceiptsEvent2Amt>24352</GrossReceiptsEvent2Amt>
        <GrossRevenueEvent2Amt>24352</GrossRevenueEvent2Amt>
        <CashPrizesEvent2Amt>12176</CashPrizesEvent2Amt>
        <OtherEventsTotalCnt>1</OtherEventsTotalCnt>
        <GrossReceiptsOtherEventsAmt>3132</GrossReceiptsOtherEventsAmt>
        <GrossRevenueOtherEventsAmt>3132</GrossRevenueOtherEventsAmt>
        <OthDirectExpnssOtherEventsAmt>368</OthDirectExpnssOtherEventsAmt>
        <GrossReceiptsTotalAmt>83810</GrossReceiptsTotalAmt>
        <GrossRevenueTotalEventsAmt>83810</GrossRevenueTotalEventsAmt>
        <CashPrizesTotalEventsAmt>13186</CashPrizesTotalEventsAmt>
        <RentFcltyCostsTotalEventsAmt>1836</RentFcltyCostsTotalEventsAmt>
        <FoodAndBeverageTotalEventsAmt>8869</FoodAndBeverageTotalEventsAmt>
        <OthDirectExpnssTotalEventsAmt>17996</OthDirectExpnssTotalEventsAmt>
        <DirectExpenseSummaryEventsAmt>41887</DirectExpenseSummaryEventsAmt>
        <NetIncomeSummaryAmt>41923</NetIncomeSummaryAmt>
      </FundraisingEventInformationGrp>
    </IRS990ScheduleG>
    <IRS990ScheduleO documentId="RetDoc1051800001">
      <SupplementalInformationDetail>
        <FormAndLineReferenceDesc>FORM 990-EZ, PART I, LINE 10 - GRANTS AND SIMILAR AMOUNTS PAID</FormAndLineReferenceDesc>
        <ExplanationTxt>ACTIVITY CLASSIFICATION: DONATION. GRANTEE NAME: ST. FRANCIS HIGH SCHOOL. GRANTEE ADDRESS: 2130 W. ROOSEVELT RD WHEATON, IL 60187. GRANTEE RELATIONSHIP: HIGH SCHOOL SUPPORTED. AMOUNT GIVEN: 43,600.</ExplanationTxt>
      </SupplementalInformationDetail>
      <SupplementalInformationDetail>
        <FormAndLineReferenceDesc>FORM 990-EZ, PART I, LINE 16 - OTHER EXPENSES</FormAndLineReferenceDesc>
        <ExplanationTxt>DESCRIPTION: ADMINISTRATIVE. AMOUNT: 1,020. DESCRIPTION: APPAREL. AMOUNT: 11,284. DESCRIPTION: CREDIT CARD PROCESSING FEES. AMOUNT: 1,983. DESCRIPTION: FEES &amp; LICENSES. AMOUNT: 30. DESCRIPTION: MEETING EXPENSES. AMOUNT: 2,838. TOTAL TO FORM 990-EZ, LINE 16: 17,155.</ExplanationTxt>
      </SupplementalInformationDetail>
      <SupplementalInformationDetail>
        <FormAndLineReferenceDesc>FORM 990-EZ, PART II, LINE 24 - OTHER ASSETS</FormAndLineReferenceDesc>
        <ExplanationTxt>DESCRIPTION: OTHER ASSET. BEG. OF YEAR AMOUNT: 0. END OF YEAR AMOUNT: 550.</ExplanationTxt>
      </SupplementalInformationDetail>
    </IRS990ScheduleO>
    <TransferPrsnlBnftContractsDecl documentId="RetDoc2278000001">
      <DeclarationDesc>THE ORGANIZATION DID NOT, DURING THE YEAR, RECEIVE ANY FUNDS, DIRECTLY,OR INDIRECTLY, TO PAY PREMIUMS ON A PERSONAL BENEFIT CONTRACT.THE ORGANIZATION, DID NOT, DURING THE YEAR, PAY ANY PREMIUMS, DIRECTLY,OR INDIRECTLY, ON A PERSONAL BENEFIT CONTRACT.</DeclarationDesc>
    </TransferPrsnlBnftContractsDecl>
  </ReturnData>
</Return>
